{
    "L1Trigger":"L1.*",
    "Photon": "Photon.*",
    "CaloMET":"CaloMET_.*",
    "ChsMET":"ChsMET_.*",
    "CorrT1METJet":"CorrT1METJet_.*",
    "nCorrT1METJet":"nCorrT1METJet",
    "DeepMETResolutionTune":"DeepMETResolutionTune_.*",
    "DeepMETResponseTune":"DeepMETResponseTune_.*",
    "FsrPhoton":"FsrPhoton_.*",
    "nFsrPhoton":"nFsrPhoton",
    "GenDressedLepton":"GenDressedLepton_.*",
    "nGenDressedLepton":"nGenDressedLepton",
    "GenIsolatedPhoton":"GenIsolatedPhoton_.*",
    "nGenIsolatedPhoton":"nGenIsolatedPhoton",
    "HLTriggerFinalPath":"HLTriggerFinalPath",
    "HLTriggerFirstPath":"HLTriggerFirstPath",
    "HTXS":"HTXS_.*",
    "IsoTrack":"IsoTrack_.*",
    "L1":"L1_.*",
    "L1Reco":"L1Reco_.*",
    "L1simulation":"L1simulation_.*",
    "LowPtElectron":"LowPtElectron_.*",
    "nLowPtElectron":"nLowPtElectron",
    "OtherPV":"OtherPV_.*",
    "nOtherPV":"nOtherPV",
    "genTtbarId":"genTtbarId.*"
}